nitropay/__init__.py
nitropay/sponsor.py
nitropay_sponsor_python-0.0.1.dist-info/METADATA
nitropay_sponsor_python-0.0.1.dist-info/WHEEL
nitropay_sponsor_python-0.0.1.dist-info/top_level.txt
nitropay_sponsor_python-0.0.1.dist-info/RECORD
